setup.cfg
setup.py
rollinghash/__init__.py
rollinghash/rollinghash.py
rollinghash.egg-info/PKG-INFO
rollinghash.egg-info/SOURCES.txt
rollinghash.egg-info/dependency_links.txt
rollinghash.egg-info/requires.txt
rollinghash.egg-info/top_level.txt
test/test_basic.py