Metadata-Version: 1.0
Name: rollinghash
Version: 0.0.1
Summary: A python rolling hash implementation
Home-page: https://github.com/wontonst/rollinghash
Author: Roy Zheng
Author-email: roycraft3@gmail.com
License: MIT
Keywords: rolling hash rollinghash
Platform: UNKNOWN
